pyqg/__init__.py
pyqg/_version.py
pyqg/bt_model.py
pyqg/diagnostic_tools.py
pyqg/kernel.cpython-36m-darwin.so
pyqg/layered_model.py
pyqg/model.py
pyqg/particles.py
pyqg/point_vortex.py
pyqg/qg_model.py
pyqg/sqg_model.py
pyqg-0.3.0.dist-info/LICENSE
pyqg-0.3.0.dist-info/METADATA
pyqg-0.3.0.dist-info/WHEEL
pyqg-0.3.0.dist-info/top_level.txt
pyqg-0.3.0.dist-info/RECORD
